{
  "environment":"local",
  "dataServiceBaseUrl":"data/",
  "fhirServiceBaseUrl":"data/",
  "cqlServiceBaseUrl":"data/",
  "libraryBaseUrl":"data/",
  "valueSetServiceBaseUrl":"data/",
  "codeSystemServiceBaseUrl":"data/",
  "configServiceBaseUrl":"data/",
  "exporterServiceBaseUrl":"data/",
  "unitServiceBaseUrl":"data/",
  "userServiceBaseUrl":"data/",
  "authenticationType":"none",
  "dashboardController":"PhekbDashboardController",
  "dashboardView":"views/phekb/dashboard.html",
  "phekbUrl": ""
}